pkg_wizard/__init__.py
pkg_wizard/cli.py
pkg_wizard/package_structure.py
pkg_wizard/content/__init__.py
pkg_wizard/content/configurations/.gitignore
pkg_wizard/content/configurations/__init__.py
pkg_wizard/content/configurations/dev_requirements.txt
pkg_wizard/content/configurations/readme.md
pkg_wizard/content/configurations/requirements.txt
pkg_wizard/content/configurations/setup.py
pkg_wizard/content/devcontainer/__init__.py
pkg_wizard/content/devcontainer/devcontainer.env
pkg_wizard/content/devcontainer/devcontainer.json
pkg_wizard/content/devcontainer/post-create.sh
pkg_wizard/content/docker/Dockerfile
pkg_wizard/content/docker/__init__.py
pkg_wizard/content/github_actions/__init__.py
pkg_wizard/content/github_actions/publish.yml
pkg_wizard/content/llm/__init__.py
pkg_wizard/content/llm/apikey_handler.py
pkg_wizard/content/llm/azurekeyvault_apikey_handler.py
pkg_wizard/content/llm/constant.py
pkg_wizard/content/llm/env_apikey_handler.py
pkg_wizard/content/llm/few_shot_learning.py
pkg_wizard/content/llm/llm.py
pkg_wizard/content/llm/llm_util.py
pkg_wizard/content/pre_commit/.pre-commit-config.yaml
pkg_wizard/content/pre_commit/__init__.py
pkg_wizard/core/__init__.py
pkg_wizard/core/configuration_support.py
pkg_wizard/core/dev_container_support.py
pkg_wizard/core/docker_support.py
pkg_wizard/core/github_action_support.py
pkg_wizard/core/init_dir.py
pkg_wizard/core/llm_support.py
pkg_wizard/core/pre_commit_support.py
pkg_wizard/core/test_support.py
pkg_wizard/utils/__init__.py
pkg_wizard/utils/file.py
pkg_wizard-1.1.5.dist-info/LICENSE
pkg_wizard-1.1.5.dist-info/METADATA
pkg_wizard-1.1.5.dist-info/WHEEL
pkg_wizard-1.1.5.dist-info/entry_points.txt
pkg_wizard-1.1.5.dist-info/top_level.txt
pkg_wizard-1.1.5.dist-info/RECORD
