Metadata-Version: 2.1
Name: pkg_wizard
Version: 1.1.5
Summary: Generate a Python package structure with optional Docker support.
Home-page: https://github.com/nadeem4/boilerplate_code
Author: Nadeem Khan
Author-email: nadeem4.nk13@gmail.com
License: MIT
Classifier: Programming Language :: Python :: 3
Classifier: Operating System :: OS Independent
Classifier: License :: OSI Approved :: MIT License
Requires-Python: >=3.6
License-File: LICENSE
